{"title":"네스트나다 ─ 인포크링크","url":"https://link.inpock.co.kr/nestnada","favicon":"https://d2t18a6mds8ktb.cloudfront.net/favicon/favicon.png?w=32&f=png","elements":[{"title":"1월 6일 목요일 7시 ﻿\"때론 나홀로 나다\" 예매 페이지 1/3(월) 오후 8시 예매 오픈!","contents":"<div class=\"link gtm-link-click-visitor\" data-v-24b900f9=\"\"><div class=\"picture-wrapper image\" data-v-1566f4d6=\"\" data-v-24b900f9=\"\"><picture data-v-1566f4d6=\"\"><source srcset=\"https://d3ojqbf8oic3ch.cloudfront.net/2022/1/1/2022-1-1-1641035142142.webp?w=300\" type=\"image/webp\" data-v-1566f4d6=\"\"> <source srcset=\"https://d3ojqbf8oic3ch.cloudfront.net/2022/1/1/2022-1-1-1641035142142.webp?w=300&amp;f=png\" type=\"image/png\" data-v-1566f4d6=\"\"> <img src=\"https://d3ojqbf8oic3ch.cloudfront.net/2022/1/1/2022-1-1-1641035142142.webp?w=300&amp;f=png\" style=\"height:100%;object-fit:cover;\" data-v-1566f4d6=\"\"></picture> <!----></div> <div class=\"link-meta\" data-v-24b900f9=\"\"><!----> <p class=\"inpock-typography paragraph-2 titleClass title\" data-v-24b900f9=\"\">1월 6일 목요일 7시 ﻿\"때론 나홀로 나다\" 예매 페이지 1/3(월) 오후 8시 예매 오픈!</p></div></div>","link":"https://link.inpock.co.kr/api/statistics/click-link?link_id=557519&user_id=36708&username=nestnada&redirect_url=https%3A%2F%2Fdocs.google.com%2Fforms%2Fd%2Fe%2F1FAIpQLSfl117wOnIT1uGynAuM9y-vahZ8Pp7lh5UDjIPXFSD7uARrgw%2Fviewform%3Fusp%3Dsf_link","retrieved":1641036212824}]}