{"title":"폼텍웍스홀 ─ 공연안내 ─ 예정공연","url":"http://www.workshall.co.kr/play/show_list.html","favicon":"http://www.workshall.co.kr/play/favicon.ico","elements":[{"title":"누군가의 플레이리스트 Track. 58 9001(나인티오원) 단독 콘서트","contents":"2022.11.26 (토) 18:00","link":"http://www.workshall.co.kr/play/show_detail.html?no=1131","retrieved":1668619988702,"image":"http://img.formtec.co.kr/formtecworks/list/listimg1_1668664579.jpg"},{"title":"누군가의 플레이리스트 Track. 58 9001(나인티오원) 단독 콘서트","contents":"2022.11.27 (일) 18:00","link":"http://www.workshall.co.kr/play/show_detail.html?no=1132","retrieved":1668619988703,"image":"http://img.formtec.co.kr/formtecworks/list/listimg1_1668664591.jpg"},{"title":"배인혁 1인 공연 : 나머지 공부","contents":"2022.11.30 (수) 20:00","link":"http://www.workshall.co.kr/play/show_detail.html?no=1168","retrieved":1668785153351,"image":"http://img.formtec.co.kr/formtecworks/list/listimg1_1666351503.jpg"},{"title":"파란，미완의 이야기","contents":"2022.12.03 (토) 18:00","link":"http://www.workshall.co.kr/play/show_detail.html?no=1172","retrieved":1668875599691,"image":"http://img.formtec.co.kr/formtecworks/list/listimg1_1669367577.jpg"},{"title":"누군가의 플레이리스트 Track. 59 새벽공방 단독 콘서트","contents":"2022.12.04 (일) 18:00","link":"http://www.workshall.co.kr/play/show_detail.html?no=1163","retrieved":1668958002728,"image":"http://img.formtec.co.kr/formtecworks/list/listimg1_1669367561.jpg"},{"title":"배인혁 1인 공연 : 나머지 공부","contents":"2022.12.07 (수) 20:00","link":"http://www.workshall.co.kr/play/show_detail.html?no=1174","retrieved":1669217122916,"image":"http://img.formtec.co.kr/formtecworks/list/listimg1_1667788124.jpg"},{"title":"문학과지성사 통합시상식","contents":"2022.12.08 (목) 17:00","link":"http://www.workshall.co.kr/play/show_detail.html?no=1156","retrieved":1669303491235,"image":"http://img.formtec.co.kr/formtecworks/list/listimg1_1665627821.jpg"},{"title":"JazzWorks n08 - Jazz Guitar","contents":"2022.12.09 (금) 20:00","link":"http://www.workshall.co.kr/play/show_detail.html?no=1157","retrieved":1669389965069,"image":"http://img.formtec.co.kr/formtecworks/list/listimg1_1669367692.jpg"}]}