{"title":"폼텍웍스홀 ─ 공연안내 ─ 예정공연","url":"http://www.workshall.co.kr/play/show_list.html","favicon":"http://www.workshall.co.kr/play/favicon.ico","elements":[{"title":"누군가의 플레이리스트 Track．64 맥거핀（MGFF）단독콘서트","contents":"2023.06.11 (일) 00:00","link":"http://www.workshall.co.kr/play/show_detail.html?no=1239","retrieved":1685028074531,"image":"http://img.formtec.co.kr/formtecworks/list/listimg1_1685866819.jpg"},{"title":"이지형 콘서트 ‘초여름 로맨스’","contents":"2023.06.17 (토) 00:00","link":"http://www.workshall.co.kr/play/show_detail.html?no=1227","retrieved":1685204688022,"image":"http://img.formtec.co.kr/formtecworks/list/listimg1_1683818002.jpg"},{"title":"이지형 콘서트 ‘초여름 로맨스’","contents":"2023.06.18 (일) 00:00","link":"http://www.workshall.co.kr/play/show_detail.html?no=1228","retrieved":1685287271770,"image":"http://img.formtec.co.kr/formtecworks/list/listimg1_1683817995.jpg"},{"title":"숨결: SUM vol.1","contents":"2023.06.24 (토) 00:00","link":"http://www.workshall.co.kr/play/show_detail.html?no=1251","retrieved":1685719240972,"image":"http://img.formtec.co.kr/formtecworks/list/listimg1_1685866930.jpg"},{"title":"JAZZ WORKS","contents":"2023.06.25 (일) 00:00","link":"http://www.workshall.co.kr/play/show_detail.html?no=1252","retrieved":1685805491386,"image":"http://img.formtec.co.kr/formtecworks/list/listimg1_1682262456.jpg"},{"title":"찰카기의 썰","contents":"2023.06.29 (목) 20:00","link":"http://www.workshall.co.kr/play/show_detail.html?no=1243","retrieved":1685891914292,"image":"http://img.formtec.co.kr/formtecworks/list/listimg1_1679562704.jpg"},{"title":"기획공연","contents":"2023.06.30 (금) 20:00","link":"http://www.workshall.co.kr/play/show_detail.html?no=1254","retrieved":1686323996588,"image":"http://img.formtec.co.kr/formtecworks/list/listimg1_1683467244.jpg"}]}